shuup_mirage_field/__init__.py
shuup_mirage_field/crypto.py
shuup_mirage_field/exceptions.py
shuup_mirage_field/fields.py
shuup_mirage_field/tools.py
shuup_mirage_field/management/__init__.py
shuup_mirage_field/management/commands/__init__.py
shuup_mirage_field/management/commands/mirage.py
shuup_mirage_field-2.1.1.dist-info/LICENSE
shuup_mirage_field-2.1.1.dist-info/METADATA
shuup_mirage_field-2.1.1.dist-info/WHEEL
shuup_mirage_field-2.1.1.dist-info/top_level.txt
shuup_mirage_field-2.1.1.dist-info/RECORD
