Metadata-Version: 2.1
Name: shuup-mirage-field
Version: 2.1.1
Summary: Shuup Mirage Field
Home-page: UNKNOWN
License: UNKNOWN
Keywords: shuup
Platform: UNKNOWN
License-File: LICENSE
Requires-Dist: django (<4,>=2)
Requires-Dist: cryptography (<4,>=3.4.7)
